wolfssl/__about__.py
wolfssl/__init__.py
wolfssl/_build_ffi.py
wolfssl/_build_wolfssl.py
wolfssl/_ffi.abi3.so
wolfssl/_methods.py
wolfssl/exceptions.py
wolfssl/utils.py
wolfssl_with_ed25519-3.14.4.post1.dist-info/METADATA
wolfssl_with_ed25519-3.14.4.post1.dist-info/RECORD
wolfssl_with_ed25519-3.14.4.post1.dist-info/WHEEL
wolfssl_with_ed25519-3.14.4.post1.dist-info/top_level.txt
